rentryco/__init__.py
rentryco-0.0.1.dist-info/METADATA
rentryco-0.0.1.dist-info/WHEEL
rentryco-0.0.1.dist-info/top_level.txt
rentryco-0.0.1.dist-info/RECORD
